<?xml version="1.0" encoding="UTF-8"?>
<gesmes:Envelope xmlns:gesmes="http://www.gesmes.org/xml/2002-08-01" xmlns="http://www.ecb.int/vocabulary/2002-08-01/eurofxref">
	<gesmes:subject>Reference rates</gesmes:subject>
	<gesmes:Sender>
		<gesmes:name>European Central Bank</gesmes:name>
	</gesmes:Sender>
	<Cube>
		<Cube time='2023-12-28'>
			<Cube currency='USD' rate='1.1114'/>
			<Cube currency='JPY' rate='156.57'/>
			<Cube currency='BGN' rate='1.9558'/>
			<Cube currency='CZK' rate='24.714'/>
			<Cube currency='DKK' rate='7.4545'/>
			<Cube currency='GBP' rate='0.87060'/>
			<Cube currency='HUF' rate='383.10'/>
			<Cube currency='PLN' rate='4.3355'/>
			<Cube currency='RON' rate='4.9753'/>
			<Cube currency='SEK' rate='11.0382'/>
			<Cube currency='CHF' rate='0.9302'/>
			<Cube currency='ISK' rate='150.30'/>
			<Cube currency='NOK' rate='11.2625'/>
			<Cube currency='TRY' rate='32.7501'/>
			<Cube currency='AUD' rate='1.6246'/>
			<Cube currency='BRL' rate='5.3739'/>
			<Cube currency='CAD' rate='1.4698'/>
			<Cube currency='CNY' rate='7.8941'/>
			<Cube currency='HKD' rate='8.6876'/>
			<Cube currency='IDR' rate='17136.79'/>
			<Cube currency='ILS' rate='4.0221'/>
			<Cube currency='INR' rate='92.4490'/>
			<Cube currency='KRW' rate='1429.08'/>
			<Cube currency='MXN' rate='18.7767'/>
			<Cube currency='MYR' rate='5.1213'/>
			<Cube currency='NZD' rate='1.7536'/>
			<Cube currency='PHP' rate='61.599'/>
			<Cube currency='SGD' rate='1.4643'/>
			<Cube currency='THB' rate='37.999'/>
			<Cube currency='ZAR' rate='20.6003'/>
		</Cube>
	</Cube>
</gesmes:Envelope>