<?xml version="1.0" encoding="UTF-8"?>
<gesmes:Envelope xmlns:gesmes="http://www.gesmes.org/xml/2002-08-01" xmlns="http://www.ecb.int/vocabulary/2002-08-01/eurofxref">
	<gesmes:subject>Reference rates</gesmes:subject>
	<gesmes:Sender>
		<gesmes:name>European Central Bank</gesmes:name>
	</gesmes:Sender>
	<Cube>
		<Cube time='2023-04-21'>
			<Cube currency='USD' rate='1.0978'/>
			<Cube currency='JPY' rate='146.92'/>
			<Cube currency='BGN' rate='1.9558'/>
			<Cube currency='CZK' rate='23.565'/>
			<Cube currency='DKK' rate='7.4527'/>
			<Cube currency='GBP' rate='0.88570'/>
			<Cube currency='HUF' rate='377.23'/>
			<Cube currency='PLN' rate='4.6108'/>
			<Cube currency='RON' rate='4.9410'/>
			<Cube currency='SEK' rate='11.3315'/>
			<Cube currency='CHF' rate='0.9795'/>
			<Cube currency='ISK' rate='150.10'/>
			<Cube currency='NOK' rate='11.6505'/>
			<Cube currency='TRY' rate='21.2999'/>
			<Cube currency='AUD' rate='1.6394'/>
			<Cube currency='BRL' rate='5.5432'/>
			<Cube currency='CAD' rate='1.4859'/>
			<Cube currency='CNY' rate='7.5619'/>
			<Cube currency='HKD' rate='8.6157'/>
			<Cube currency='IDR' rate='16423.09'/>
			<Cube currency='ILS' rate='4.0175'/>
			<Cube currency='INR' rate='90.1090'/>
			<Cube currency='KRW' rate='1458.64'/>
			<Cube currency='MXN' rate='19.7623'/>
			<Cube currency='MYR' rate='4.8715'/>
			<Cube currency='NZD' rate='1.7913'/>
			<Cube currency='PHP' rate='61.401'/>
			<Cube currency='SGD' rate='1.4651'/>
			<Cube currency='THB' rate='37.731'/>
			<Cube currency='ZAR' rate='19.8967'/>
		</Cube>
	</Cube>
</gesmes:Envelope>