<?xml version="1.0" encoding="UTF-8"?>
<gesmes:Envelope xmlns:gesmes="http://www.gesmes.org/xml/2002-08-01" xmlns="http://www.ecb.int/vocabulary/2002-08-01/eurofxref">
	<gesmes:subject>Reference rates</gesmes:subject>
	<gesmes:Sender>
		<gesmes:name>European Central Bank</gesmes:name>
	</gesmes:Sender>
	<Cube>
		<Cube time='2023-10-05'>
			<Cube currency='USD' rate='1.0526'/>
			<Cube currency='JPY' rate='156.71'/>
			<Cube currency='BGN' rate='1.9558'/>
			<Cube currency='CZK' rate='24.416'/>
			<Cube currency='DKK' rate='7.4578'/>
			<Cube currency='GBP' rate='0.86605'/>
			<Cube currency='HUF' rate='387.08'/>
			<Cube currency='PLN' rate='4.5988'/>
			<Cube currency='RON' rate='4.9703'/>
			<Cube currency='SEK' rate='11.5975'/>
			<Cube currency='CHF' rate='0.9625'/>
			<Cube currency='ISK' rate='145.30'/>
			<Cube currency='NOK' rate='11.5703'/>
			<Cube currency='TRY' rate='29.0064'/>
			<Cube currency='AUD' rate='1.6580'/>
			<Cube currency='BRL' rate='5.4372'/>
			<Cube currency='CAD' rate='1.4479'/>
			<Cube currency='CNY' rate='7.6856'/>
			<Cube currency='HKD' rate='8.2412'/>
			<Cube currency='IDR' rate='16426.14'/>
			<Cube currency='ILS' rate='4.0667'/>
			<Cube currency='INR' rate='87.6270'/>
			<Cube currency='KRW' rate='1420.44'/>
			<Cube currency='MXN' rate='19.0209'/>
			<Cube currency='MYR' rate='4.9762'/>
			<Cube currency='NZD' rate='1.7715'/>
			<Cube currency='PHP' rate='59.661'/>
			<Cube currency='SGD' rate='1.4421'/>
			<Cube currency='THB' rate='38.883'/>
			<Cube currency='ZAR' rate='20.5884'/>
		</Cube>
	</Cube>
</gesmes:Envelope>