<?xml version="1.0" encoding="UTF-8"?>
<gesmes:Envelope xmlns:gesmes="http://www.gesmes.org/xml/2002-08-01" xmlns="http://www.ecb.int/vocabulary/2002-08-01/eurofxref">
	<gesmes:subject>Reference rates</gesmes:subject>
	<gesmes:Sender>
		<gesmes:name>European Central Bank</gesmes:name>
	</gesmes:Sender>
	<Cube>
		<Cube time='2026-02-02'>
			<Cube currency='USD' rate='1.1840'/>
			<Cube currency='JPY' rate='183.59'/>
			<Cube currency='CZK' rate='24.305'/>
			<Cube currency='DKK' rate='7.4691'/>
			<Cube currency='GBP' rate='0.86580'/>
			<Cube currency='HUF' rate='381.20'/>
			<Cube currency='PLN' rate='4.2173'/>
			<Cube currency='RON' rate='5.0960'/>
			<Cube currency='SEK' rate='10.5935'/>
			<Cube currency='CHF' rate='0.9199'/>
			<Cube currency='ISK' rate='145.00'/>
			<Cube currency='NOK' rate='11.4655'/>
			<Cube currency='TRY' rate='51.4941'/>
			<Cube currency='AUD' rate='1.7042'/>
			<Cube currency='BRL' rate='6.2222'/>
			<Cube currency='CAD' rate='1.6157'/>
			<Cube currency='CNY' rate='8.2210'/>
			<Cube currency='HKD' rate='9.2484'/>
			<Cube currency='IDR' rate='19890.00'/>
			<Cube currency='ILS' rate='3.6738'/>
			<Cube currency='INR' rate='108.4170'/>
			<Cube currency='KRW' rate='1719.74'/>
			<Cube currency='MXN' rate='20.6131'/>
			<Cube currency='MYR' rate='4.6673'/>
			<Cube currency='NZD' rate='1.9705'/>
			<Cube currency='PHP' rate='69.754'/>
			<Cube currency='SGD' rate='1.5055'/>
			<Cube currency='THB' rate='37.432'/>
			<Cube currency='ZAR' rate='18.9774'/>
		</Cube>
	</Cube>
</gesmes:Envelope>