<?xml version="1.0" encoding="UTF-8"?>
<gesmes:Envelope xmlns:gesmes="http://www.gesmes.org/xml/2002-08-01" xmlns="http://www.ecb.int/vocabulary/2002-08-01/eurofxref">
	<gesmes:subject>Reference rates</gesmes:subject>
	<gesmes:Sender>
		<gesmes:name>European Central Bank</gesmes:name>
	</gesmes:Sender>
	<Cube>
		<Cube time='2025-07-17'>
			<Cube currency='USD' rate='1.1579'/>
			<Cube currency='JPY' rate='172.28'/>
			<Cube currency='BGN' rate='1.9558'/>
			<Cube currency='CZK' rate='24.639'/>
			<Cube currency='DKK' rate='7.4628'/>
			<Cube currency='GBP' rate='0.86440'/>
			<Cube currency='HUF' rate='399.15'/>
			<Cube currency='PLN' rate='4.2544'/>
			<Cube currency='RON' rate='5.0734'/>
			<Cube currency='SEK' rate='11.3110'/>
			<Cube currency='CHF' rate='0.9323'/>
			<Cube currency='ISK' rate='141.80'/>
			<Cube currency='NOK' rate='11.9675'/>
			<Cube currency='TRY' rate='46.6446'/>
			<Cube currency='AUD' rate='1.7923'/>
			<Cube currency='BRL' rate='6.4624'/>
			<Cube currency='CAD' rate='1.5937'/>
			<Cube currency='CNY' rate='8.3157'/>
			<Cube currency='HKD' rate='9.0883'/>
			<Cube currency='IDR' rate='18931.49'/>
			<Cube currency='ILS' rate='3.8901'/>
			<Cube currency='INR' rate='99.6725'/>
			<Cube currency='KRW' rate='1614.66'/>
			<Cube currency='MXN' rate='21.7782'/>
			<Cube currency='MYR' rate='4.9170'/>
			<Cube currency='NZD' rate='1.9587'/>
			<Cube currency='PHP' rate='66.312'/>
			<Cube currency='SGD' rate='1.4904'/>
			<Cube currency='THB' rate='37.678'/>
			<Cube currency='ZAR' rate='20.7253'/>
		</Cube>
	</Cube>
</gesmes:Envelope>